MANIFEST.in
README
README.rst
setup.cfg
setup.py
spacegrids/__init__.py
spacegrids/_config.py
spacegrids/_iosg.py
spacegrids/abstract.py
spacegrids/decorators.py
spacegrids/expercls.py
spacegrids/fieldcls.py
spacegrids/ops.py
spacegrids/plotting.py
spacegrids/projectcls.py
spacegrids/utilsg.py
spacegrids.egg-info/PKG-INFO
spacegrids.egg-info/SOURCES.txt
spacegrids.egg-info/dependency_links.txt
spacegrids.egg-info/pbr.json
spacegrids.egg-info/top_level.txt