Metadata-Version: 1.1
Name: spacegrids
Version: 1.9
Summary: numpy array with grids and associated operations
Home-page: https://github.com/willo12/spacegrids
Author: Willem Sijp
Author-email: wim.sijp@gmail.com
License: BSD
Download-URL: https://github.com/willo12/spacegrids/tarball/1.8
Keywords: climate data,grid data,data on grids,spatial grids,Netcdf data analysis,climate analysis scripts,interpreting meta data Netcdf,geophysics tools
Platform: UNKNOWN
